novafitness_sds018/__init__.py
novafitness_sds018/novafitness_sds018.py
novafitness_sds018-0.0.4.dist-info/LICENSE
novafitness_sds018-0.0.4.dist-info/METADATA
novafitness_sds018-0.0.4.dist-info/WHEEL
novafitness_sds018-0.0.4.dist-info/top_level.txt
novafitness_sds018-0.0.4.dist-info/RECORD
